.hgignore
CHANGES.txt
README.txt
bootstrap.py
setup.py
profiles/base.cfg
profiles/dev.cfg
profiles/prod.cfg
profiles/versions.cfg
src/gocept/__init__.py
src/gocept.bender.egg-info/PKG-INFO
src/gocept.bender.egg-info/SOURCES.txt
src/gocept.bender.egg-info/dependency_links.txt
src/gocept.bender.egg-info/entry_points.txt
src/gocept.bender.egg-info/namespace_packages.txt
src/gocept.bender.egg-info/not-zip-safe
src/gocept.bender.egg-info/requires.txt
src/gocept.bender.egg-info/top_level.txt
src/gocept/bender/__init__.py
src/gocept/bender/bot.py
src/gocept/bender/http.py
src/gocept/bender/interfaces.py
src/gocept/bender/quote.py
src/gocept/bender/quote.txt
src/gocept/bender/tests/__init__.py
src/gocept/bender/tests/test_http.py
src/gocept/bender/tests/test_quote.py