Metadata-Version: 1.0
Name: gocept.bender
Version: 1.0
Summary: A Jabber-Bot that can be told things to say via XML-RPC.
